hesmapy/__about__.py
hesmapy/__init__.py
hesmapy/base.py
hesmapy/constants.py
hesmapy/json_base.py
hesmapy/hydro/__init__.py
hesmapy/hydro/hydro1d.py
hesmapy/hydro/utils.py
hesmapy/rt/__init__.py
hesmapy/rt/lightcurves.py
hesmapy/rt/spectra.py
hesmapy/utils/__init__.py
hesmapy/utils/plot_utils.py
hesmapy/utils/writer_utils.py
hesmapy/writers/__init__.py
hesmapy/writers/hydro1d.py
hesmapy/writers/rt_lightcurve.py
hesmapy/writers/rt_spectrum.py
hesmapy-24.4.1.dist-info/METADATA
hesmapy-24.4.1.dist-info/WHEEL
hesmapy-24.4.1.dist-info/licenses/LICENSE
hesmapy-24.4.1.dist-info/RECORD
