Metadata-Version: 2.3
Name: hesmapy
Version: 24.4.1
Summary: HESMA file format reader and writer
Project-URL: Homepage, https://github.com/alexhls/hesmapy
Project-URL: Bug Tracker, https://github.com/alexhls/hesmapy/issues
Author-email: Alexander Holas <alex.holas@gmx.de>
License-File: LICENSE
Classifier: License :: OSI Approved :: GNU General Public License v3 (GPLv3)
Classifier: Operating System :: OS Independent
Classifier: Programming Language :: Python :: 3
Requires-Python: >=3.11
Requires-Dist: jsonschema
Requires-Dist: numpy>=1.26
Requires-Dist: pandas>=2.1
Requires-Dist: plotly>=5.18
Provides-Extra: docs
Requires-Dist: furo; extra == 'docs'
Requires-Dist: sphinx; extra == 'docs'
Requires-Dist: sphinx-copybutton; extra == 'docs'
